pcr_optimizer/__init__.py
pcr_optimizer/pcrprotocoloptimizer.py
pcr_optimizer-0.13.dist-info/LICENSE
pcr_optimizer-0.13.dist-info/METADATA
pcr_optimizer-0.13.dist-info/WHEEL
pcr_optimizer-0.13.dist-info/top_level.txt
pcr_optimizer-0.13.dist-info/RECORD
