Metadata-Version: 2.1
Name: pcr-optimizer
Version: 0.13
Summary: A function for PCR protocal optimization
Home-page: https://github.com/Ara101/PCR_Optimization_class.git
Author: Lily Torp, K. Lionel Tukei 
Author-email: ltorp3@uw.edu, ltukei@uw.edu
Classifier: Development Status :: 3 - Alpha
Classifier: Intended Audience :: Science/Research
Classifier: Topic :: Scientific/Engineering
Classifier: License :: OSI Approved :: MIT License
Classifier: Programming Language :: Python :: 3.9
Classifier: Programming Language :: Python :: 3.10
Classifier: Programming Language :: Python :: 3.11
License-File: LICENSE
